LICENSE.txt
setup.py
superpy/README.txt
superpy/__init__.py
superpy.egg-info/PKG-INFO
superpy.egg-info/SOURCES.txt
superpy.egg-info/dependency_links.txt
superpy.egg-info/requires.txt
superpy.egg-info/top_level.txt
superpy/demos/pyfog/fogGUI.py
superpy/scripts/CleanOldTasks.py
superpy/scripts/ShowServer.py
superpy/scripts/Spawn.py
superpy/scripts/SpawnAsService.py
superpy/scripts/StartSuperWatch.py
superpyMisc/__init__.py
superpyMisc/ez_setup.py
superpyMisc/googlecode_upload.py
superpyMisc/release_instructions.txt
superpyTesting/__init__.py
superpyTesting/_test.py
superpyTesting/unitTestsFromSrc.py
superpy/SuperWatch/GUIUtils.py
superpy/SuperWatch/GUIValidators.py
superpy/SuperWatch/MsgWindow.py
superpy/SuperWatch/Periodicity.py
superpy/SuperWatch/SPGui.py
superpy/SuperWatch/SPWidgets.py
superpy/SuperWatch/SuperInfo.py
superpy/SuperWatch/__init__.py
superpy/core/DataStructures.py
superpy/core/Forker.py
superpy/core/Manager.py
superpy/core/PicklingXMLRPC.py
superpy/core/Process.py
superpy/core/Servers.py
superpy/core/TaskInfo.py
superpy/core/Tasks.py
superpy/core/__init__.py
superpy/core/config.py
superpy/demos/__init__.py
superpy/demos/pyfog/__init__.py
superpy/demos/pyfog/_testFogMaker.py
superpy/demos/pyfog/feedparser.py
superpy/demos/pyfog/fogConfig.py
superpy/demos/pyfog/fogGUI.py
superpy/demos/pyfog/fogMaker.py
superpy/demos/pyfog/fogger.py
superpy/demos/pyfog/ignores.py
superpy/demos/pyfog/defaults/__init__.py
superpy/demos/pyfog/defaults/exampleRSS.txt
superpy/demos/pyfog/defaults/exampleWebs.txt
superpy/scripts/CleanOldTasks.py
superpy/scripts/ShowServer.py
superpy/scripts/Spawn.py
superpy/scripts/SpawnAsService.py
superpy/scripts/StartSuperWatch.py
superpy/scripts/__init__.py
superpy/utils/WindowsSubprocess.py
superpy/utils/WindowsUtils.py
superpy/utils/__init__.py
superpy/utils/winprocess.py