Metadata-Version: 1.1
Name: superpy
Version: 1.2.6
Summary: Parallel processing tools for supercomputing with python.
Home-page: http://code.google.com/p/superpy/
Author: Emin Martinian, Li Lee, Henry Xu
Author-email: emin.martinian@gmail.com
License: MIT
Keywords: parallel,super,process
Platform: UNKNOWN
Provides: superpy
